pyliblinear/__init__.py
pyliblinear/_liblinear.cpython-314t-x86_64-linux-musl.so
pyliblinear.libs/libgcc_s-0cd532bd.so.1
pyliblinear.libs/libstdc++-5d72f927.so.6.0.33
pyliblinear-249.1.dist-info/METADATA
pyliblinear-249.1.dist-info/WHEEL
pyliblinear-249.1.dist-info/top_level.txt
pyliblinear-249.1.dist-info/RECORD
pyliblinear-249.1.dist-info/licenses/LICENSE
